pyRecFusionSDK/__init__.py
pyRecFusionSDK/_pyRecFusionSDK_impl.pyd
pyrecfusionsdk-0.1.1.dist-info/METADATA
pyrecfusionsdk-0.1.1.dist-info/WHEEL
pyrecfusionsdk-0.1.1.dist-info/RECORD
