Metadata-Version: 2.1
Name: pyrecfusionsdk
Version: 0.1.1
Summary: Python wrapper around the RecFusionSDK library
Author-Email: Patryk Kiepas <kiepas.patryk@gmail.com>
Classifier: License :: OSI Approved :: MIT License
Project-URL: Homepage, https://github.com/quepas/pyRecFusionSDK
Requires-Python: >=3.11
Requires-Dist: numpy>=2.3.2
Provides-Extra: dev
Requires-Dist: pytest>=8.4.1; extra == "dev"
